Assignment 2/Code/que_1.v
module gray_ctr
  (input 	clk,
	input 	rstn,
	output reg [3:0] out);

	reg [3:0] temp;

	always @ (posedge clk) begin
		if (!rstn) begin
    	temp <= 0;
    		out <= 0;
      end else begin
  		temp <= temp + 1;

`ifdef for_loop
    	for (int i = 0; i < 3; i= i+1) begin
      	out[i] <= temp[i+1] ^ temp[i];
    	end
    	out[3] <= temp[3];
`else
			out <= {temp[3], temp[3:1] ^ temp[2:0]};
`endif
    end
	end
endmodule

Assignment 2/Code/que_1_tb.v
module q1;
  reg clk;
  reg reset;
  wire [3:0] out;

  gray_ctr q1 (.clk(clk), .rstn(reset), .out(out));

  always #10 clk = ~clk;

  initial begin
    {clk, reset} <= 0;
    $dumpfile("q1.vcd");
    $dumpvars(0,q1);
    $monitor ("Time = %0t  Reset = %b  Output = %b ", $time, reset, out);

    repeat(2) @ (posedge clk);
    reset <= 1;
    repeat(19) @ (posedge clk);
    $finish;
  end
endmodule

Assignment 2/Code/q1.vcd
$date
	Mon Mar 14 21:29:54 2022
$end
$version
	Icarus Verilog
$end
$timescale
	1s
$end
$scope module q1 $end
$scope module q1 $end
$var wire 1 ! clk $end
$var wire 1 " rstn $end
$var reg 4 # out [3:0] $end
$var reg 4 $ temp [3:0] $end
$upscope $end
$upscope $end
$enddefinitions $end
#0
$dumpvars
bx $
bx #
0"
0!
$end
#10
b0 #
b0 $
1!
#20
0!
#30
1"
1!
#40
0!
#50
b1 $
1!
#60
0!
#70
b1 #
b10 $
1!
#80
0!
#90
b11 #
b11 $
1!
#100
0!
#110
b10 #
b100 $
1!
#120
0!
#130
b110 #
b101 $
1!
#140
0!
#150
b111 #
b110 $
1!
#160
0!
#170
b101 #
b111 $
1!
#180
0!
#190
b100 #
b1000 $
1!
#200
0!
#210
b1100 #
b1001 $
1!
#220
0!
#230
b1101 #
b1010 $
1!
#240
0!
#250
b1111 #
b1011 $
1!
#260
0!
#270
b1110 #
b1100 $
1!
#280
0!
#290
b1010 #
b1101 $
1!
#300
0!
#310
b1011 #
b1110 $
1!
#320
0!
#330
b1001 #
b1111 $
1!
#340
0!
#350
b1000 #
b0 $
1!
#360
0!
#370
b0 #
b1 $
1!
#380
0!
#390
b1 #
b10 $
1!
#400
0!
#410
b11 #
b11 $
1!
