Assignment 2/Code/q2_farzi.v
module ring_counter (
      input clock,
      input reset,
      output [3:0] out
    );
 
  reg[3:0] temp;
 
    always @(posedge clock)
      if (reset)
        temp = 4'b1000;
      else
        begin
         temp = {temp[0]^temp[1],temp[3:1]};
        end
    assign out = temp;
 
  endmodule

Assignment 2/Code/q2_farzi_tb.v
`timescale 1ns / 1ps
module q2;
	reg clock;
	reg reset;
   wire[3:0] out;
	ring_counter r2 (
      .clock(clock), 
      .reset(reset), 
      .out(out)
	);
 
  always #10 clock = ~clock;
 
	initial begin
   clock = 0;  
	reset = 0;
	#5 reset = 1;
	#20 reset = 0; 
	#300 $finish;
    end  
 
		initial begin
         $dumpfile("q2.vcd");
         $dumpvars(0,q2);
         $monitor($time, " Clock = %1b , Reset = %1b , Output = %4b ",clock,reset,out);
		 end
 
endmodule

Assignment 2/Code/q2.vcd
$date
	Mon Mar 14 21:25:36 2022
$end
$version
	Icarus Verilog
$end
$timescale
	1ps
$end
$scope module q2 $end
$var wire 4 ! out [3:0] $end
$var reg 1 " clock $end
$var reg 1 # reset $end
$scope module r2 $end
$var wire 1 " clock $end
$var wire 4 $ out [3:0] $end
$var wire 1 # reset $end
$var reg 4 % temp [3:0] $end
$upscope $end
$upscope $end
$enddefinitions $end
#0
$dumpvars
bx %
bx $
0#
0"
bx !
$end
#5000
1#
#10000
b1000 !
b1000 $
b1000 %
1"
#20000
0"
#25000
0#
#30000
b100 !
b100 $
b100 %
1"
#40000
0"
#50000
b10 !
b10 $
b10 %
1"
#60000
0"
#70000
b1001 !
b1001 $
b1001 %
1"
#80000
0"
#90000
b1100 !
b1100 $
b1100 %
1"
#100000
0"
#110000
b110 !
b110 $
b110 %
1"
#120000
0"
#130000
b1011 !
b1011 $
b1011 %
1"
#140000
0"
#150000
b101 !
b101 $
b101 %
1"
#160000
0"
#170000
b1010 !
b1010 $
b1010 %
1"
#180000
0"
#190000
b1101 !
b1101 $
b1101 %
1"
#200000
0"
#210000
b1110 !
b1110 $
b1110 %
1"
#220000
0"
#230000
b1111 !
b1111 $
b1111 %
1"
#240000
0"
#250000
b111 !
b111 $
b111 %
1"
#260000
0"
#270000
b11 !
b11 $
b11 %
1"
#280000
0"
#290000
b1 !
b1 $
b1 %
1"
#300000
0"
#310000
b1000 !
b1000 $
b1000 %
1"
